collective.confirmableforms-2.1.2-py2.7-nspkg.pth
collective/confirmableforms/__init__.py
collective/confirmableforms/browser.py
collective/confirmableforms/config.py
collective/confirmableforms/configure.zcml
collective/confirmableforms/interfaces.py
collective/confirmableforms/mailer.py
collective/confirmableforms/patches.py
collective/confirmableforms/rebuild_i18n.sh
collective/confirmableforms/setuphandlers.py
collective/confirmableforms/tests.py
collective/confirmableforms/tests.txt
collective/confirmableforms/utils.py
collective/confirmableforms/content/__init__.py
collective/confirmableforms/content/confirmedFormMailerAdapter.py
collective/confirmableforms/locales/collective.confirmableforms.pot
collective/confirmableforms/locales/plone.pot
collective/confirmableforms/locales/fr/LC_MESSAGES/collective.confirmableforms.mo
collective/confirmableforms/locales/fr/LC_MESSAGES/collective.confirmableforms.po
collective/confirmableforms/locales/fr/LC_MESSAGES/plone.mo
collective/confirmableforms/locales/fr/LC_MESSAGES/plone.po
collective/confirmableforms/locales/nl/LC_MESSAGES/collective.confirmableforms.mo
collective/confirmableforms/locales/nl/LC_MESSAGES/collective.confirmableforms.po
collective/confirmableforms/locales/nl/LC_MESSAGES/plone.mo
collective/confirmableforms/locales/nl/LC_MESSAGES/plone.po
collective/confirmableforms/profiles/default/metadata.xml
collective/confirmableforms/profiles/default/propertiestool.xml
collective/confirmableforms/profiles/default/rolemap.xml
collective/confirmableforms/profiles/default/types.xml
collective/confirmableforms/profiles/default/workflows.xml
collective/confirmableforms/profiles/default/types/ConfirmedFormMailerAdapter.xml
collective/confirmableforms/profiles/default/types/FormFolder.xml
collective/confirmableforms/templates/form_confirmed_error.pt
collective.confirmableforms-2.1.2.dist-info/METADATA
collective.confirmableforms-2.1.2.dist-info/WHEEL
collective.confirmableforms-2.1.2.dist-info/entry_points.txt
collective.confirmableforms-2.1.2.dist-info/namespace_packages.txt
collective.confirmableforms-2.1.2.dist-info/top_level.txt
collective.confirmableforms-2.1.2.dist-info/RECORD
