Metadata-Version: 2.1
Name: collective.confirmableforms
Version: 2.1.2
Summary: A Plone add on to simplify form confirmation by e-mail.
Home-page: https://github.com/zestsoftware/collective.confirmableforms
Author: Vincent Pretre
Author-email: v.pretre@zestsoftware.nl
License: GPL
Keywords: PloneFormGen confirmation email
Platform: UNKNOWN
Classifier: Development Status :: 5 - Production/Stable
Classifier: Framework :: Plone
Classifier: Framework :: Plone :: 4.3
Classifier: License :: OSI Approved :: GNU General Public License (GPL)
Classifier: Programming Language :: Python
Classifier: Programming Language :: Python :: 2.7
Requires-Dist: setuptools
Requires-Dist: Products.PloneFormGen
Requires-Dist: collective.depositbox
Requires-Dist: collective.monkeypatcher
Provides-Extra: test
Requires-Dist: Products.PloneTestCase ; extra == 'test'
